fusion/__init__.py
fusion/__main__.py
fusion/_fusion.py
fusion/attributes.py
fusion/authentication.py
fusion/credentials.py
fusion/data_dependency.py
fusion/dataflow.py
fusion/dataset.py
fusion/embeddings.py
fusion/embeddings_utils.py
fusion/exceptions.py
fusion/fs_sync.py
fusion/fusion.py
fusion/fusion_filesystem.py
fusion/fusion_types.py
fusion/product.py
fusion/py.typed
fusion/report.py
fusion/report_attributes.py
fusion/types.py
fusion/utils.py
fusion/_legacy/__init__.py
fusion/_legacy/authentication.py
pyfusion-4.0.0.dist-info/licenses/LICENSE
pyfusion-4.0.0.dist-info/METADATA
pyfusion-4.0.0.dist-info/WHEEL
pyfusion-4.0.0.dist-info/top_level.txt
pyfusion-4.0.0.dist-info/RECORD
